LICENSE.txt
MANIFEST.in
README.md
README.rst
ez_setup.py
setup.py
hgross/__init__.py
hgross/racelog.py
hgross/speedwise_ftp.py
hgross/speedwise_node.py
hgross/ac/ACLogParser.py
hgross/ac/ACRequestTools.py
hgross/ac/ACServerWrapper.py
hgross/ac/__init__.py
hgross/ac/ac_server.py
hgross/ac/common.py
hgross/crypt/__init__.py
hgross/speedwise/__init__.py
hgross/speedwise/speedwise_client.py
hgross/speedwise/util.py
speedwise_node.egg-info/PKG-INFO
speedwise_node.egg-info/SOURCES.txt
speedwise_node.egg-info/dependency_links.txt
speedwise_node.egg-info/entry_points.txt
speedwise_node.egg-info/requires.txt
speedwise_node.egg-info/top_level.txt