Metadata-Version: 1.1
Name: speedwise-node
Version: 0.3.6
Summary: This is the server node module to connect your Assetto Corsa game servers with speedwise.de.
Home-page: http://speedwise.de
Author: Henning Gross
Author-email: mail.to <at> henning-gross <dot> de
License: MIT
Keywords: assetto corsa,ac,speedwise,stats,statistics,monitoring,banlist,server,dedicated server,gameserver,game,racing
Platform: UNKNOWN
Classifier: Environment :: Win32 (MS Windows)
Classifier: Operating System :: Microsoft :: Windows :: Windows NT/2000
Classifier: Operating System :: Microsoft
Classifier: Operating System :: POSIX :: Linux
Classifier: Operating System :: POSIX
Classifier: Programming Language :: Python :: 2.7
Classifier: Topic :: System :: Networking
Classifier: Topic :: System :: Systems Administration
Classifier: Topic :: Utilities
Classifier: Topic :: Software Development :: Libraries :: Python Modules
Classifier: Topic :: Software Development :: Libraries
